{
  "annotations": {
    "list": [
      {
        "builtIn": 1,
        "datasource": "-- Plutono --",
        "enable": true,
        "hide": true,
        "iconColor": "rgba(0, 211, 255, 1)",
        "name": "Annotations & Alerts",
        "type": "dashboard"
      }
    ]
  },
  "editable": true,
  "gnetId": null,
  "graphTooltip": 1,
  "id": 2,
  "iteration": 1575634591795,
  "links": [],
  "panels": [
    {
      "collapsed": false,
      "datasource": null,
      "gridPos": {
        "h": 1,
        "w": 24,
        "x": 0,
        "y": 0
      },
      "id": 20,
      "panels": [],
      "title": "Total Alerts Overview",
      "type": "row"
    },
    {
      "datasource": null,
      "description": "Shows the number of alerts by infrastructure.",
      "fieldConfig": {
        "defaults": {
          "color": {
            "mode": "thresholds"
          },
          "decimals": 0,
          "displayName": "",
          "mappings": [],
          "max": 100,
          "min": 0,
          "thresholds": {
            "mode": "absolute",
            "steps": [
              {
                "color": "green",
                "value": null
              },
              {
                "color": "red",
                "value": 80
              }
            ]
          }
        },
        "overrides": []
      },
      "gridPos": {
        "h": 8,
        "w": 9,
        "x": 0,
        "y": 1
      },
      "id": 26,
      "options": {
        "displayMode": "gradient",
        "orientation": "horizontal",
        "reduceOptions": {
          "calcs": [
            "lastNotNull"
          ],
          "fields": "",
          "values": false
        },
        "showUnfilled": true,
        "text": {}
      },
      "pluginVersion": "7.5.23",
      "targets": [
        {
          "expr": "count(ALERTS{severity=~\"$Severity\", alertstate=~\"$AlertState\", alertname=~\"$Alertname\", shoot_infra=~\"$Infra\"}) by (shoot_infra)",
          "instant": true,
          "legendFormat": "{{shoot_infra}}",
          "refId": "A"
        }
      ],
      "timeFrom": null,
      "timeShift": null,
      "title": "Alerts by Infrastructure  ($Severity|$AlertState|$Alertname|$Infra)",
      "type": "bargauge"
    },
    {
      "cacheTimeout": null,
      "colorBackground": false,
      "colorValue": true,
      "colors": [
        "#F2495C",
        "#F2495C",
        "#F2495C"
      ],
      "datasource": null,
      "decimals": 0,
      "description": "Shows how many alerts are currently firing for shoots using this seed.",
      "fieldConfig": {
        "defaults": {},
        "overrides": []
      },
      "format": "none",
      "gauge": {
        "maxValue": 100,
        "minValue": 0,
        "show": false,
        "thresholdLabels": false,
        "thresholdMarkers": true
      },
      "gridPos": {
        "h": 4,
        "w": 5,
        "x": 9,
        "y": 1
      },
      "id": 11,
      "interval": null,
      "links": [],
      "mappingType": 1,
      "mappingTypes": [
        {
          "name": "value to text",
          "value": 1
        },
        {
          "name": "range to text",
          "value": 2
        }
      ],
      "maxDataPoints": 100,
      "nullPointMode": "connected",
      "nullText": null,
      "postfix": "Firing Alert(s)",
      "postfixFontSize": "50%",
      "prefix": "",
      "prefixFontSize": "50%",
      "rangeMaps": [
        {
          "from": "null",
          "text": "N/A",
          "to": "null"
        }
      ],
      "sparkline": {
        "fillColor": "rgba(31, 118, 189, 0.18)",
        "full": false,
        "lineColor": "rgb(31, 120, 193)",
        "show": false
      },
      "tableColumn": "",
      "targets": [
        {
          "expr": "count(ALERTS{alertstate=\"firing\"})",
          "format": "time_series",
          "instant": true,
          "intervalFactor": 1,
          "refId": "A"
        }
      ],
      "thresholds": "",
      "timeFrom": null,
      "timeShift": null,
      "title": "Firing Alerts",
      "type": "singlestat",
      "valueFontSize": "80%",
      "valueMaps": [
        {
          "op": "=",
          "text": "0",
          "value": "null"
        }
      ],
      "valueName": "avg"
    },
    {
      "cacheTimeout": null,
      "colorBackground": false,
      "colorValue": true,
      "colors": [
        "#FF9830",
        "#FF9830",
        "#FF9830"
      ],
      "datasource": null,
      "decimals": 0,
      "description": "Shows how many alerts are currently pending for shoots using this seed.",
      "fieldConfig": {
        "defaults": {},
        "overrides": []
      },
      "format": "none",
      "gauge": {
        "maxValue": 100,
        "minValue": 0,
        "show": false,
        "thresholdLabels": false,
        "thresholdMarkers": true
      },
      "gridPos": {
        "h": 4,
        "w": 5,
        "x": 14,
        "y": 1
      },
      "id": 12,
      "interval": null,
      "links": [],
      "mappingType": 1,
      "mappingTypes": [
        {
          "name": "value to text",
          "value": 1
        },
        {
          "name": "range to text",
          "value": 2
        }
      ],
      "maxDataPoints": 100,
      "nullPointMode": "connected",
      "nullText": null,
      "postfix": " Pending Alert(s)",
      "postfixFontSize": "50%",
      "prefix": "",
      "prefixFontSize": "50%",
      "rangeMaps": [
        {
          "from": "null",
          "text": "N/A",
          "to": "null"
        }
      ],
      "sparkline": {
        "fillColor": "rgba(31, 118, 189, 0.18)",
        "full": false,
        "lineColor": "rgb(31, 120, 193)",
        "show": false
      },
      "tableColumn": "",
      "targets": [
        {
          "expr": "count(ALERTS{alertstate=\"pending\"})",
          "format": "time_series",
          "instant": true,
          "intervalFactor": 1,
          "refId": "A"
        }
      ],
      "thresholds": "",
      "timeFrom": null,
      "timeShift": null,
      "title": "Pending Alerts",
      "type": "singlestat",
      "valueFontSize": "80%",
      "valueMaps": [
        {
          "op": "=",
          "text": "0",
          "value": "null"
        }
      ],
      "valueName": "avg"
    },
    {
      "cacheTimeout": null,
      "datasource": null,
      "description": "Shows the percentage of clusters that have at least 1 firing or pending alert.",
      "fieldConfig": {
        "defaults": {
          "color": {
            "mode": "thresholds"
          },
          "decimals": null,
          "mappings": [
            {
              "from": "",
              "id": 1,
              "operator": "",
              "text": "0",
              "to": "",
              "type": 1,
              "value": "null"
            },
            {
              "from": "",
              "id": 2,
              "operator": "",
              "text": "0",
              "to": "",
              "type": 1,
              "value": "No data"
            }
          ],
          "max": 100,
          "min": 0,
          "thresholds": {
            "mode": "absolute",
            "steps": [
              {
                "color": "green",
                "value": null
              },
              {
                "color": "red",
                "value": 50
              }
            ]
          },
          "unit": "percent"
        },
        "overrides": []
      },
      "gridPos": {
        "h": 4,
        "w": 5,
        "x": 19,
        "y": 1
      },
      "id": 16,
      "links": [],
      "options": {
        "orientation": "auto",
        "reduceOptions": {
          "calcs": [
            "mean"
          ],
          "fields": "",
          "values": false
        },
        "showThresholdLabels": false,
        "showThresholdMarkers": false,
        "text": {}
      },
      "pluginVersion": "7.5.23",
      "targets": [
        {
          "expr": "count(count(ALERTS) by (shoot_name)) / count(count(shoot:availability) by (shoot_name)) * 100",
          "format": "time_series",
          "instant": true,
          "intervalFactor": 1,
          "refId": "A"
        }
      ],
      "timeFrom": null,
      "timeShift": null,
      "title": "% of Clusters with Alerts",
      "type": "gauge"
    },
    {
      "cacheTimeout": null,
      "colorBackground": false,
      "colorValue": true,
      "colors": [
        "#F2495C",
        "#F2495C",
        "#F2495C"
      ],
      "datasource": null,
      "decimals": 0,
      "description": "Shows how many clusters have at least 1 firing alert.",
      "fieldConfig": {
        "defaults": {},
        "overrides": []
      },
      "format": "none",
      "gauge": {
        "maxValue": 100,
        "minValue": 0,
        "show": false,
        "thresholdLabels": false,
        "thresholdMarkers": true
      },
      "gridPos": {
        "h": 4,
        "w": 5,
        "x": 9,
        "y": 5
      },
      "id": 17,
      "interval": null,
      "links": [],
      "mappingType": 1,
      "mappingTypes": [
        {
          "name": "value to text",
          "value": 1
        },
        {
          "name": "range to text",
          "value": 2
        }
      ],
      "maxDataPoints": 100,
      "nullPointMode": "connected",
      "nullText": null,
      "postfix": "Cluster(s)",
      "postfixFontSize": "50%",
      "prefix": "",
      "prefixFontSize": "50%",
      "rangeMaps": [
        {
          "from": "null",
          "text": "N/A",
          "to": "null"
        }
      ],
      "sparkline": {
        "fillColor": "rgba(31, 118, 189, 0.18)",
        "full": false,
        "lineColor": "rgb(31, 120, 193)",
        "show": false
      },
      "tableColumn": "",
      "targets": [
        {
          "expr": "count(count(ALERTS{alertstate=\"firing\"}) by (shoot_name))",
          "format": "time_series",
          "instant": true,
          "intervalFactor": 1,
          "legendFormat": "",
          "refId": "A"
        }
      ],
      "thresholds": "",
      "timeFrom": null,
      "timeShift": null,
      "title": "Clusters with Firing Alerts",
      "type": "singlestat",
      "valueFontSize": "80%",
      "valueMaps": [
        {
          "op": "=",
          "text": "0",
          "value": "null"
        }
      ],
      "valueName": "avg"
    },
    {
      "cacheTimeout": null,
      "colorBackground": false,
      "colorValue": true,
      "colors": [
        "#FF9830",
        "#FF9830",
        "#FF9830"
      ],
      "datasource": null,
      "decimals": 0,
      "description": "Shows how many clusters currently have at least 1 pending alert.",
      "fieldConfig": {
        "defaults": {},
        "overrides": []
      },
      "format": "none",
      "gauge": {
        "maxValue": 100,
        "minValue": 0,
        "show": false,
        "thresholdLabels": false,
        "thresholdMarkers": true
      },
      "gridPos": {
        "h": 4,
        "w": 5,
        "x": 14,
        "y": 5
      },
      "id": 18,
      "interval": null,
      "links": [],
      "mappingType": 1,
      "mappingTypes": [
        {
          "name": "value to text",
          "value": 1
        },
        {
          "name": "range to text",
          "value": 2
        }
      ],
      "maxDataPoints": 100,
      "nullPointMode": "connected",
      "nullText": null,
      "postfix": " Cluster(s)",
      "postfixFontSize": "50%",
      "prefix": "",
      "prefixFontSize": "50%",
      "rangeMaps": [
        {
          "from": "null",
          "text": "N/A",
          "to": "null"
        }
      ],
      "sparkline": {
        "fillColor": "rgba(31, 118, 189, 0.18)",
        "full": false,
        "lineColor": "rgb(31, 120, 193)",
        "show": false
      },
      "tableColumn": "",
      "targets": [
        {
          "expr": "count(count(ALERTS{alertstate=\"pending\"}) by (shoot_name))",
          "format": "time_series",
          "instant": true,
          "intervalFactor": 1,
          "legendFormat": "",
          "refId": "A"
        }
      ],
      "thresholds": "",
      "timeFrom": null,
      "timeShift": null,
      "title": "Clusters with Pending Alerts",
      "type": "singlestat",
      "valueFontSize": "80%",
      "valueMaps": [
        {
          "op": "=",
          "text": "0",
          "value": "null"
        }
      ],
      "valueName": "avg"
    },
    {
      "cacheTimeout": null,
      "colorBackground": false,
      "colorValue": false,
      "colors": [
        "#299c46",
        "rgba(237, 129, 40, 0.89)",
        "#d44a3a"
      ],
      "datasource": null,
      "description": "Shows the total number of shoots with a control plane on this seed.",
      "fieldConfig": {
        "defaults": {},
        "overrides": []
      },
      "format": "none",
      "gauge": {
        "maxValue": 100,
        "minValue": 0,
        "show": false,
        "thresholdLabels": false,
        "thresholdMarkers": true
      },
      "gridPos": {
        "h": 4,
        "w": 5,
        "x": 19,
        "y": 5
      },
      "id": 14,
      "interval": null,
      "links": [],
      "mappingType": 1,
      "mappingTypes": [
        {
          "name": "value to text",
          "value": 1
        },
        {
          "name": "range to text",
          "value": 2
        }
      ],
      "maxDataPoints": 100,
      "nullPointMode": "connected",
      "nullText": null,
      "postfix": "Cluster(s)",
      "postfixFontSize": "50%",
      "prefix": "",
      "prefixFontSize": "50%",
      "rangeMaps": [
        {
          "from": "null",
          "text": "N/A",
          "to": "null"
        }
      ],
      "sparkline": {
        "fillColor": "rgba(31, 118, 189, 0.18)",
        "full": false,
        "lineColor": "rgb(31, 120, 193)",
        "show": false
      },
      "tableColumn": "",
      "targets": [
        {
          "expr": "count(count(shoot:availability) by (shoot_name))",
          "format": "time_series",
          "instant": true,
          "intervalFactor": 1,
          "legendFormat": "",
          "refId": "A"
        }
      ],
      "thresholds": "",
      "timeFrom": null,
      "timeShift": null,
      "title": "Clusters Total",
      "type": "singlestat",
      "valueFontSize": "80%",
      "valueMaps": [
        {
          "op": "=",
          "text": "N/A",
          "value": "null"
        }
      ],
      "valueName": "avg"
    },
    {
      "aliasColors": {},
      "bars": false,
      "dashLength": 10,
      "dashes": false,
      "datasource": null,
      "decimals": 0,
      "description": "Shows alerts that are/were active with the selected severity and alert state from the selected clusters. Includes the alertnames of the alerts.",
      "fieldConfig": {
        "defaults": {
          "links": []
        },
        "overrides": []
      },
      "fill": 0,
      "fillGradient": 0,
      "gridPos": {
        "h": 8,
        "w": 24,
        "x": 0,
        "y": 9
      },
      "hiddenSeries": false,
      "id": 24,
      "legend": {
        "alignAsTable": true,
        "avg": false,
        "current": true,
        "max": false,
        "min": false,
        "rightSide": true,
        "show": true,
        "total": false,
        "values": true
      },
      "lines": true,
      "linewidth": 1,
      "links": [],
      "nullPointMode": "null",
      "options": {
        "alertThreshold": true
      },
      "percentage": false,
      "pluginVersion": "7.5.23",
      "pointradius": 2,
      "points": false,
      "renderer": "flot",
      "seriesOverrides": [],
      "spaceLength": 10,
      "stack": false,
      "steppedLine": false,
      "targets": [
        {
          "expr": "count(ALERTS{alertname=~\"$Alertname\", severity=~\"$Severity\", alertstate=~\"$AlertState\", shoot_infra=~\"$Infra\"}) by (alertname)",
          "format": "time_series",
          "intervalFactor": 1,
          "legendFormat": "{{ alertname }}",
          "refId": "A"
        }
      ],
      "thresholds": [],
      "timeFrom": null,
      "timeRegions": [],
      "timeShift": null,
      "title": "Active Alerts ($Severity|$AlertState|$Alertname|$Infra)",
      "tooltip": {
        "shared": false,
        "sort": 0,
        "value_type": "individual"
      },
      "type": "graph",
      "xaxis": {
        "buckets": null,
        "mode": "time",
        "name": null,
        "show": true,
        "values": []
      },
      "yaxes": [
        {
          "decimals": 0,
          "format": "short",
          "label": null,
          "logBase": 1,
          "max": null,
          "min": null,
          "show": true
        },
        {
          "format": "short",
          "label": null,
          "logBase": 1,
          "max": null,
          "min": null,
          "show": true
        }
      ],
      "yaxis": {
        "align": false,
        "alignLevel": null
      }
    },
    {
      "collapsed": false,
      "datasource": null,
      "gridPos": {
        "h": 1,
        "w": 24,
        "x": 0,
        "y": 17
      },
      "id": 22,
      "panels": [],
      "title": "Alerts by Cluster",
      "type": "row"
    },
    {
      "aliasColors": {},
      "bars": false,
      "dashLength": 10,
      "dashes": false,
      "datasource": null,
      "decimals": 0,
      "description": "Shows the number of alerts in each cluster.",
      "fieldConfig": {
        "defaults": {
          "links": []
        },
        "overrides": []
      },
      "fill": 0,
      "fillGradient": 0,
      "gridPos": {
        "h": 10,
        "w": 24,
        "x": 0,
        "y": 18
      },
      "hiddenSeries": false,
      "id": 4,
      "interval": "",
      "legend": {
        "alignAsTable": true,
        "avg": false,
        "current": true,
        "max": false,
        "min": false,
        "rightSide": true,
        "show": true,
        "total": false,
        "values": true
      },
      "lines": true,
      "linewidth": 1,
      "links": [],
      "nullPointMode": "null",
      "options": {
        "alertThreshold": true
      },
      "percentage": false,
      "pluginVersion": "7.5.23",
      "pointradius": 2,
      "points": false,
      "renderer": "flot",
      "seriesOverrides": [],
      "spaceLength": 10,
      "stack": false,
      "steppedLine": false,
      "targets": [
        {
          "expr": "count(ALERTS{alertname=~\"$Alertname\", severity=~\"$Severity\", alertstate=~\"$AlertState\", shoot_infra=~\"$Infra\"}) by (project,name)",
          "format": "time_series",
          "intervalFactor": 1,
          "legendFormat": "{{ project }}/{{ name }}",
          "refId": "A"
        }
      ],
      "thresholds": [],
      "timeFrom": null,
      "timeRegions": [],
      "timeShift": null,
      "title": "Cluster Alert Count ($Severity|$AlertState|$Alertname|$Infra)",
      "tooltip": {
        "shared": false,
        "sort": 0,
        "value_type": "individual"
      },
      "type": "graph",
      "xaxis": {
        "buckets": null,
        "mode": "time",
        "name": null,
        "show": true,
        "values": []
      },
      "yaxes": [
        {
          "decimals": 0,
          "format": "short",
          "label": "Alerts",
          "logBase": 1,
          "max": null,
          "min": "0",
          "show": true
        },
        {
          "decimals": null,
          "format": "short",
          "label": null,
          "logBase": 1,
          "max": null,
          "min": null,
          "show": true
        }
      ],
      "yaxis": {
        "align": false,
        "alignLevel": null
      }
    },
    {
      "columns": [],
      "datasource": null,
      "description": "Shows all alerts that are currently active from the selected clusters, severity, and alert state.",
      "fieldConfig": {
        "defaults": {},
        "overrides": []
      },
      "fontSize": "100%",
      "gridPos": {
        "h": 12,
        "w": 24,
        "x": 0,
        "y": 28
      },
      "id": 7,
      "links": [],
      "pageSize": null,
      "scroll": true,
      "showHeader": true,
      "sort": {
        "col": 0,
        "desc": true
      },
      "styles": [
        {
          "alias": "Time",
          "align": "auto",
          "dateFormat": "YYYY-MM-DD HH:mm:ss",
          "pattern": "Time",
          "type": "hidden"
        },
        {
          "alias": "",
          "align": "auto",
          "colorMode": null,
          "colors": [
            "rgba(245, 54, 54, 0.9)",
            "rgba(237, 129, 40, 0.89)",
            "rgba(50, 172, 45, 0.97)"
          ],
          "dateFormat": "YYYY-MM-DD HH:mm:ss",
          "decimals": 2,
          "mappingType": 1,
          "pattern": "Value",
          "thresholds": [],
          "type": "hidden",
          "unit": "short"
        },
        {
          "alias": "",
          "align": "auto",
          "colorMode": null,
          "colors": [
            "rgba(245, 54, 54, 0.9)",
            "rgba(237, 129, 40, 0.89)",
            "rgba(50, 172, 45, 0.97)"
          ],
          "dateFormat": "YYYY-MM-DD HH:mm:ss",
          "decimals": 2,
          "link": true,
          "linkTooltip": "",
          "linkUrl": "/d/shoot-details/shoot-details?orgId=1&refresh=30s&var-project=${__cell_3}&var-shoot=${__cell}",
          "mappingType": 1,
          "pattern": "name",
          "thresholds": [],
          "type": "string",
          "unit": "short"
        },
        {
          "alias": "",
          "align": "auto",
          "colorMode": null,
          "colors": [
            "rgba(245, 54, 54, 0.9)",
            "rgba(237, 129, 40, 0.89)",
            "rgba(50, 172, 45, 0.97)"
          ],
          "decimals": 0,
          "pattern": "/.*/",
          "thresholds": [],
          "type": "number",
          "unit": "short"
        }
      ],
      "targets": [
        {
          "expr": "count(ALERTS{severity=~\"$Severity\",alertname=~\"$Alertname\", alertstate=~\"$AlertState\",shoot_infra=~\"$Infra\"}) by (alertname, project,shoot_name, severity, alertstate, shoot_infra)",
          "format": "table",
          "instant": true,
          "intervalFactor": 1,
          "legendFormat": "",
          "refId": "A"
        }
      ],
      "timeFrom": null,
      "timeShift": null,
      "title": "Cluster Alerts ($Severity|$AlertState|$Alertname|$Infra)",
      "transform": "table",
      "type": "table-old"
    }
  ],
  "refresh": false,
  "schemaVersion": 27,
  "style": "dark",
  "tags": [
    "monitoring",
    "seed"
  ],
  "templating": {
    "list": [
      {
        "allValue": null,
        "current": {
          "selected": true,
          "text": [
            "All"
          ],
          "value": [
            "$__all"
          ]
        },
        "datasource": "prometheus",
        "definition": "label_values(ALERTS,severity)",
        "description": null,
        "error": null,
        "hide": 0,
        "includeAll": true,
        "label": null,
        "multi": true,
        "name": "Severity",
        "options": [],
        "query": {
          "query": "label_values(ALERTS,severity)",
          "refId": "prometheus-Severity-Variable-Query"
        },
        "refresh": 2,
        "regex": "",
        "skipUrlSync": false,
        "sort": 0,
        "tagValuesQuery": "",
        "tags": [],
        "tagsQuery": "",
        "type": "query",
        "useTags": false
      },
      {
        "allValue": null,
        "current": {
          "selected": true,
          "text": [
            "All"
          ],
          "value": [
            "$__all"
          ]
        },
        "datasource": "prometheus",
        "definition": "label_values(ALERTS,alertstate)",
        "description": null,
        "error": null,
        "hide": 0,
        "includeAll": true,
        "label": "Alert State",
        "multi": true,
        "name": "AlertState",
        "options": [],
        "query": {
          "query": "label_values(ALERTS,alertstate)",
          "refId": "prometheus-AlertState-Variable-Query"
        },
        "refresh": 2,
        "regex": "",
        "skipUrlSync": false,
        "sort": 0,
        "tagValuesQuery": "",
        "tags": [],
        "tagsQuery": "",
        "type": "query",
        "useTags": false
      },
      {
        "allValue": null,
        "current": {
          "selected": true,
          "text": [
            "All"
          ],
          "value": [
            "$__all"
          ]
        },
        "datasource": "prometheus",
        "definition": "label_values(ALERTS, alertname)",
        "description": null,
        "error": null,
        "hide": 0,
        "includeAll": true,
        "label": null,
        "multi": true,
        "name": "Alertname",
        "options": [],
        "query": {
          "query": "label_values(ALERTS, alertname)",
          "refId": "prometheus-Alertname-Variable-Query"
        },
        "refresh": 2,
        "regex": "",
        "skipUrlSync": false,
        "sort": 0,
        "tagValuesQuery": "",
        "tags": [],
        "tagsQuery": "",
        "type": "query",
        "useTags": false
      },
      {
        "allValue": null,
        "current": {
          "selected": true,
          "text": [
            "All"
          ],
          "value": [
            "$__all"
          ]
        },
        "datasource": "prometheus",
        "definition": "label_values(ALERTS, shoot_infra)",
        "description": null,
        "error": null,
        "hide": 0,
        "includeAll": true,
        "label": null,
        "multi": true,
        "name": "Infra",
        "options": [],
        "query": {
          "query": "label_values(ALERTS, shoot_infra)",
          "refId": "prometheus-Infra-Variable-Query"
        },
        "refresh": 2,
        "regex": "",
        "skipUrlSync": false,
        "sort": 0,
        "tagValuesQuery": "",
        "tags": [],
        "tagsQuery": "",
        "type": "query",
        "useTags": false
      }
    ]
  },
  "time": {
    "from": "now-30m",
    "to": "now"
  },
  "timepicker": {
    "refresh_intervals": [
      "5s",
      "10s",
      "30s",
      "1m",
      "5m",
      "15m",
      "30m",
      "1h",
      "2h",
      "1d"
    ],
    "time_options": [
      "5m",
      "15m",
      "1h",
      "6h",
      "12h",
      "24h",
      "2d",
      "7d",
      "30d"
    ]
  },
  "timezone": "",
  "title": "Alerts",
  "uid": "Alerts",
  "version": 1
}
